src/__init__.py
src/api_client.py
src/cli.py
src/code_storage.py
src/config_manager.py
src/error_handler.py
src/logger.py
src/session_manager.py
openwiz-1.3.6.dist-info/LICENSE
openwiz-1.3.6.dist-info/METADATA
openwiz-1.3.6.dist-info/WHEEL
openwiz-1.3.6.dist-info/entry_points.txt
openwiz-1.3.6.dist-info/top_level.txt
openwiz-1.3.6.dist-info/RECORD
