Metadata-Version: 2.1
Name: openwiz
Version: 1.3.6
Summary: A CLI tool for generating code using the OpenAI API
Home-page: https://github.com/basith-ahmed/openwiz
Author: Basith Ahmed
Author-email: basithahmeddd@gmail.com
Classifier: Programming Language :: Python :: 3
Classifier: License :: OSI Approved :: MIT License
Classifier: Operating System :: OS Independent
License-File: LICENSE
Requires-Dist: openai
Requires-Dist: pyyaml
Requires-Dist: click
Requires-Dist: pytest
